[
  {
    "Id": 348,
    "Object": "radical",
    "Url": "https://api.wanikani.com/v2/subjects/348",
    "DataUpdatedAt": "2025-10-01T06:09:49.162493Z",
    "Data": {
      "AmalgamationSubjectIds": [
        1545,
        1885,
        2300
      ],
      "Characters": "呉",
      "CharacterImages": [
        {
          "Url": "https://files.wanikani.com/b4o7aca2icgikmc3mfadmeinfin2",
          "ContentType": "image/png",
          "Metadata": {
            "ValueKind": 1
          }
        },
        {
          "Url": "https://files.wanikani.com/qdkaz5pk2wosuuqo0av7000t9szz",
          "ContentType": "image/png",
          "Metadata": {
            "ValueKind": 1
          }
        },
        {
          "Url": "https://files.wanikani.com/2p8pw2519oqn38rbkz5lcrln6uou",
          "ContentType": "image/png",
          "Metadata": {
            "ValueKind": 1
          }
        },
        {
          "Url": "https://files.wanikani.com/yo5wlffh2zir110u36bdsyn3s7md",
          "ContentType": "image/png",
          "Metadata": {
            "ValueKind": 1
          }
        },
        {
          "Url": "https://files.wanikani.com/qfi6h8cdnu2um85f07p4z959rjld",
          "ContentType": "image/png",
          "Metadata": {
            "ValueKind": 1
          }
        },
        {
          "Url": "https://files.wanikani.com/6as3eqed38ylkzeaudp0klq80av9",
          "ContentType": "image/png",
          "Metadata": {
            "ValueKind": 1
          }
        },
        {
          "Url": "https://files.wanikani.com/omjf37aggl0i5pup9r79j489bk6m",
          "ContentType": "image/png",
          "Metadata": {
            "ValueKind": 1
          }
        },
        {
          "Url": "https://files.wanikani.com/0ojif6utj0mt97ihp4qdceuv5116",
          "ContentType": "image/svg+xml",
          "Metadata": {
            "ValueKind": 1
          }
        }
      ],
      "AuxiliaryMeanings": [],
      "CreatedAt": "2013-04-05T17:51:34.845527Z",
      "DocumentUrl": "https://www.wanikani.com/radicals/catapult",
      "HiddenAt": null,
      "LessonPosition": 0,
      "Level": 34,
      "MeaningMnemonic": "See the rock in the <radical>catapult</radical>? It even has little legs to hold it steady so it can catapult better.",
      "Meanings": [
        {
          "Meaning": "Catapult",
          "Primary": true,
          "AcceptedAnswer": true
        }
      ],
      "Slug": "catapult",
      "SpacedRepetitionSystemId": 1
    }
  },
  {
    "Id": 349,
    "Object": "radical",
    "Url": "https://api.wanikani.com/v2/subjects/349",
    "DataUpdatedAt": "2025-10-01T06:09:49.161911Z",
    "Data": {
      "AmalgamationSubjectIds": [
        1573
      ],
      "Characters": "員",
      "CharacterImages": [
        {
          "Url": "https://files.wanikani.com/ipp36jjf4o8d567o659bgnrm95ks",
          "ContentType": "image/png",
          "Metadata": {
            "ValueKind": 1
          }
        },
        {
          "Url": "https://files.wanikani.com/d3vp000kgwuo1wl9tqgxkictlpww",
          "ContentType": "image/png",
          "Metadata": {
            "ValueKind": 1
          }
        },
        {
          "Url": "https://files.wanikani.com/h1aujqy5dtd5ecotagwytix97284",
          "ContentType": "image/png",
          "Metadata": {
            "ValueKind": 1
          }
        },
        {
          "Url": "https://files.wanikani.com/ai4fm2d9n1aqo4x0aldfg16btynq",
          "ContentType": "image/png",
          "Metadata": {
            "ValueKind": 1
          }
        },
        {
          "Url": "https://files.wanikani.com/e6dk6h70ql1wvaii03kcu8hmv046",
          "ContentType": "image/png",
          "Metadata": {
            "ValueKind": 1
          }
        },
        {
          "Url": "https://files.wanikani.com/lrxiqfng34865oik0yj370mfoqfc",
          "ContentType": "image/png",
          "Metadata": {
            "ValueKind": 1
          }
        },
        {
          "Url": "https://files.wanikani.com/e1puy2hjqxhaa5b3zqhchhye1qnc",
          "ContentType": "image/png",
          "Metadata": {
            "ValueKind": 1
          }
        },
        {
          "Url": "https://files.wanikani.com/69tyss2edngxmo75lb609nj391g4",
          "ContentType": "image/svg+xml",
          "Metadata": {
            "ValueKind": 1
          }
        }
      ],
      "AuxiliaryMeanings": [],
      "CreatedAt": "2013-04-05T17:51:44.765591Z",
      "DocumentUrl": "https://www.wanikani.com/radicals/member",
      "HiddenAt": null,
      "LessonPosition": 1,
      "Level": 34,
      "MeaningMnemonic": "This radical is the same as the kanji. It means <radical>member</radical>.",
      "Meanings": [
        {
          "Meaning": "Member",
          "Primary": true,
          "AcceptedAnswer": true
        }
      ],
      "Slug": "member",
      "SpacedRepetitionSystemId": 1
    }
  },
  {
    "Id": 350,
    "Object": "radical",
    "Url": "https://api.wanikani.com/v2/subjects/350",
    "DataUpdatedAt": "2025-10-01T06:09:49.163137Z",
    "Data": {
      "AmalgamationSubjectIds": [
        1575
      ],
      "Characters": "爪",
      "CharacterImages": [
        {
          "Url": "https://files.wanikani.com/lm9pc22u807w4l5g6zbi82cxvuvu",
          "ContentType": "image/png",
          "Metadata": {
            "ValueKind": 1
          }
        },
        {
          "Url": "https://files.wanikani.com/kaar3jo55pztkkjjafah44bd23ba",
          "ContentType": "image/png",
          "Metadata": {
            "ValueKind": 1
          }
        },
        {
          "Url": "https://files.wanikani.com/bmul60fk8m6dgk84gbgunaw0c6ro",
          "ContentType": "image/png",
          "Metadata": {
            "ValueKind": 1
          }
        },
        {
          "Url": "https://files.wanikani.com/0nel23vq6b2awd5r02bubhvwo5ph",
          "ContentType": "image/png",
          "Metadata": {
            "ValueKind": 1
          }
        },
        {
          "Url": "https://files.wanikani.com/zcmrnj4du3fp2lz38yf5stwp3qg7",
          "ContentType": "image/png",
          "Metadata": {
            "ValueKind": 1
          }
        },
        {
          "Url": "https://files.wanikani.com/0h0ynxmsei9omojagscgxarclf9m",
          "ContentType": "image/png",
          "Metadata": {
            "ValueKind": 1
          }
        },
        {
          "Url": "https://files.wanikani.com/72vz2o1vij9v78gci20yprwsh2cx",
          "ContentType": "image/png",
          "Metadata": {
            "ValueKind": 1
          }
        },
        {
          "Url": "https://files.wanikani.com/5h15ysaix42dpms958rhabodfqcg",
          "ContentType": "image/svg+xml",
          "Metadata": {
            "ValueKind": 1
          }
        }
      ],
      "AuxiliaryMeanings": [],
      "CreatedAt": "2013-04-05T17:51:56.811369Z",
      "DocumentUrl": "https://www.wanikani.com/radicals/claw",
      "HiddenAt": null,
      "LessonPosition": 2,
      "Level": 34,
      "MeaningMnemonic": "This looks like a <radical>claw</radical> of some kind already, making it quite easy!",
      "Meanings": [
        {
          "Meaning": "Claw",
          "Primary": true,
          "AcceptedAnswer": true
        }
      ],
      "Slug": "claw",
      "SpacedRepetitionSystemId": 1
    }
  },
  {
    "Id": 351,
    "Object": "radical",
    "Url": "https://api.wanikani.com/v2/subjects/351",
    "DataUpdatedAt": "2025-10-01T06:09:49.1649Z",
    "Data": {
      "AmalgamationSubjectIds": [
        1577,
        1626,
        2269,
        2452,
        8968
      ],
      "Characters": "亥",
      "CharacterImages": [
        {
          "Url": "https://files.wanikani.com/4iltjegt2gx5g0571or6vl3nxrx9",
          "ContentType": "image/png",
          "Metadata": {
            "ValueKind": 1
          }
        },
        {
          "Url": "https://files.wanikani.com/zwvs70mvid8n36do8xfkwoymoqhz",
          "ContentType": "image/png",
          "Metadata": {
            "ValueKind": 1
          }
        },
        {
          "Url": "https://files.wanikani.com/oc9ncuekyv1vbs5f9f54zjr1d7ym",
          "ContentType": "image/png",
          "Metadata": {
            "ValueKind": 1
          }
        },
        {
          "Url": "https://files.wanikani.com/mkys00klrs5co7w454nc2s7ui0hc",
          "ContentType": "image/png",
          "Metadata": {
            "ValueKind": 1
          }
        },
        {
          "Url": "https://files.wanikani.com/8r9s6t65qzjlqlg4zzfny3vzkbti",
          "ContentType": "image/png",
          "Metadata": {
            "ValueKind": 1
          }
        },
        {
          "Url": "https://files.wanikani.com/98wmyy1ia9m0q9w78ar4odmdivcy",
          "ContentType": "image/png",
          "Metadata": {
            "ValueKind": 1
          }
        },
        {
          "Url": "https://files.wanikani.com/tn5ctbhoup7125wfwdug9c6m9e93",
          "ContentType": "image/png",
          "Metadata": {
            "ValueKind": 1
          }
        },
        {
          "Url": "https://files.wanikani.com/7n0gn8q2nb3z98enpbuqvqbh5109",
          "ContentType": "image/svg+xml",
          "Metadata": {
            "ValueKind": 1
          }
        }
      ],
      "AuxiliaryMeanings": [],
      "CreatedAt": "2013-04-05T17:52:11.673781Z",
      "DocumentUrl": "https://www.wanikani.com/radicals/slice",
      "HiddenAt": null,
      "LessonPosition": 3,
      "Level": 34,
      "MeaningMnemonic": "See the guy? See how he was CUT IN HALF??? That must have been one heckuva <radical>slice</radical> to do that to a person.",
      "Meanings": [
        {
          "Meaning": "Slice",
          "Primary": true,
          "AcceptedAnswer": true
        }
      ],
      "Slug": "slice",
      "SpacedRepetitionSystemId": 1
    }
  },
  {
    "Id": 358,
    "Object": "radical",
    "Url": "https://api.wanikani.com/v2/subjects/358",
    "DataUpdatedAt": "2026-02-17T08:00:25.476362Z",
    "Data": {
      "AmalgamationSubjectIds": [
        1547,
        1616,
        9395
      ],
      "Characters": "貴",
      "CharacterImages": [
        {
          "Url": "https://files.wanikani.com/3xbaa5hfh1ucs5omjodslw46nu0o",
          "ContentType": "image/png",
          "Metadata": {
            "ValueKind": 1
          }
        },
        {
          "Url": "https://files.wanikani.com/o2nnjb2mey5ltu6kucymkwiur37r",
          "ContentType": "image/png",
          "Metadata": {
            "ValueKind": 1
          }
        },
        {
          "Url": "https://files.wanikani.com/r44kb8niuobiand0dauj9ebb0e51",
          "ContentType": "image/png",
          "Metadata": {
            "ValueKind": 1
          }
        },
        {
          "Url": "https://files.wanikani.com/k4fk74sfi1hkvy0r5o6jbhd0u29c",
          "ContentType": "image/png",
          "Metadata": {
            "ValueKind": 1
          }
        },
        {
          "Url": "https://files.wanikani.com/wjktwldxu9p13o89er7bh5j3fm38",
          "ContentType": "image/png",
          "Metadata": {
            "ValueKind": 1
          }
        },
        {
          "Url": "https://files.wanikani.com/fbjpwjpcnsolqge3ns6vrt4trh5t",
          "ContentType": "image/png",
          "Metadata": {
            "ValueKind": 1
          }
        },
        {
          "Url": "https://files.wanikani.com/16mqdf9f6qufxj35zz6tyn85fjod",
          "ContentType": "image/png",
          "Metadata": {
            "ValueKind": 1
          }
        },
        {
          "Url": "https://files.wanikani.com/qbx6m89rnrhjryhilhatj3iba38l",
          "ContentType": "image/svg+xml",
          "Metadata": {
            "ValueKind": 1
          }
        }
      ],
      "AuxiliaryMeanings": [
        {
          "Meaning": "Precious",
          "Type": "whitelist"
        }
      ],
      "CreatedAt": "2013-05-03T08:24:49.595452Z",
      "DocumentUrl": "https://www.wanikani.com/radicals/valuable",
      "HiddenAt": null,
      "LessonPosition": 10,
      "Level": 34,
      "MeaningMnemonic": "There's a shellfish, but it's got some kind of fancy headgear. Is that… a crown, perhaps? It looks really <radical>valuable</radical> — and the shellfish wearing it must be even more valuable to be worthy of such a status symbol!\n\nAlternatively, you can remember this radical with its components: in the middle of the ground, there's a shellfish. Why? 'Cause it's super valuable. The safest place to keep a valuable shellfish is buried in the middle of the ground.",
      "Meanings": [
        {
          "Meaning": "Valuable",
          "Primary": true,
          "AcceptedAnswer": true
        }
      ],
      "Slug": "valuable",
      "SpacedRepetitionSystemId": 1
    }
  }
]